{
  "base_price": 1950,
  "beamstation_catalog_url": "https://beamstation.com/datasets",
  "beamstation_origin": "https://beamstation.com",
  "category_group_name": "Restaurants",
  "config_category": "census",
  "config_description": "Detailed restaurant dataset for Salt Lake City, Utah with a population of over 199k. Filtered by the Restaurants category group, providing business profiles, review counts, contact information, and competitive benchmarks. Refreshed weekly.",
  "config_name": "All Restaurants in Salt Lake City, Utah, US",
  "export_job_id": "a578f7ae-9671-4e1c-837b-6416d2094b62",
  "github_org": "Beamstation-Datasets",
  "id_short": 431924,
  "location_name": "Salt Lake City",
  "location_type": "city",
  "repo_name": "all-restaurants-in-salt-lake-city-utah-us-sample-431924",
  "sample_b2_path": "b2-export:BeamStation-ExportFiles/431924/beamstation_431924_restaurants-us-ut_SAMPLE_DIST.csv",
  "sample_pct": 9.93,
  "sample_records": 86,
  "sample_sha256": "b9c16d89b986758039691780b30c5d607ada8e50243d648404efdaee5d540fb5",
  "sample_size_bytes": 338748,
  "total_records": 866,
  "updated_at": "2026-04-09T09:37:19.090276+00:00"
}